termgraphicslib/canvas.py
termgraphicslib-0.1.2.1.dist-info/LICENSE
termgraphicslib-0.1.2.1.dist-info/WHEEL
termgraphicslib-0.1.2.1.dist-info/METADATA
termgraphicslib-0.1.2.1.dist-info/RECORD
